{
  "id": "b3678744f16842debd1f2d57fbe12e9c",
  "price": {
    "totalPaymentPrice": {
      "paymentCurrencyAmount": 89900,
      "paymentCurrencyCode": "RUB",
      "paymentCurrencyExchangeRate": 1,
      "paymentCurrencySymbol": "₽"
    },
    "totalPrice": {
      "basePayoutCurrencyCode": "USD",
      "basePayoutPrice": 996,
      "convenienceFee": 0,
      "currencyCode": "RUB",
      "discount": 0,
      "discountPrice": 89900,
      "originalPrice": 89900,
      "originalUnitPrice": null,
      "unitPrice": null,
      "vat": 14983,
      "voucherDiscount": 0
    }
  }
}