{
  "id": "32d80b384c934b89be96dd4c32b54946",
  "price": {
    "totalPaymentPrice": {
      "paymentCurrencyAmount": 6699,
      "paymentCurrencyCode": "SAR",
      "paymentCurrencyExchangeRate": 1,
      "paymentCurrencySymbol": "ر.س"
    },
    "totalPrice": {
      "basePayoutCurrencyCode": "USD",
      "basePayoutPrice": 1786,
      "convenienceFee": 0,
      "currencyCode": "SAR",
      "discount": 0,
      "discountPrice": 6699,
      "originalPrice": 6699,
      "originalUnitPrice": null,
      "unitPrice": null,
      "vat": 0,
      "voucherDiscount": 0
    }
  }
}