{
  "id": "5354dc63819f416a80ef712d9d410351",
  "price": {
    "totalPaymentPrice": {
      "paymentCurrencyAmount": 3749,
      "paymentCurrencyCode": "SAR",
      "paymentCurrencyExchangeRate": 1,
      "paymentCurrencySymbol": "ر.س"
    },
    "totalPrice": {
      "basePayoutCurrencyCode": "USD",
      "basePayoutPrice": 1000,
      "convenienceFee": 0,
      "currencyCode": "SAR",
      "discount": 3750,
      "discountPrice": 3749,
      "originalPrice": 7499,
      "originalUnitPrice": null,
      "unitPrice": null,
      "vat": 0,
      "voucherDiscount": 0
    }
  }
}