{
  "id": "21da750de4f448eb981a43b2cd216c4d",
  "price": {
    "totalPaymentPrice": {
      "paymentCurrencyAmount": 990,
      "paymentCurrencyCode": "TRY",
      "paymentCurrencyExchangeRate": 1,
      "paymentCurrencySymbol": "₺"
    },
    "totalPrice": {
      "basePayoutCurrencyCode": "USD",
      "basePayoutPrice": 111,
      "convenienceFee": 0,
      "currencyCode": "TRY",
      "discount": 810,
      "discountPrice": 990,
      "originalPrice": 1800,
      "originalUnitPrice": null,
      "unitPrice": null,
      "vat": 151,
      "voucherDiscount": 0
    }
  }
}