{
  "id": "4848610565cd4563b26b0d7fc40ad307",
  "price": {
    "totalPaymentPrice": {
      "paymentCurrencyAmount": 7699,
      "paymentCurrencyCode": "TRY",
      "paymentCurrencyExchangeRate": 1,
      "paymentCurrencySymbol": "₺"
    },
    "totalPrice": {
      "basePayoutCurrencyCode": "USD",
      "basePayoutPrice": 875,
      "convenienceFee": 0,
      "currencyCode": "TRY",
      "discount": 0,
      "discountPrice": 7699,
      "originalPrice": 7699,
      "originalUnitPrice": null,
      "unitPrice": null,
      "vat": 1174,
      "voucherDiscount": 0
    }
  }
}