{
  "id": "4db76762e1364e4b8025584541b7dd1b",
  "price": {
    "totalPaymentPrice": {
      "paymentCurrencyAmount": 26900,
      "paymentCurrencyCode": "TRY",
      "paymentCurrencyExchangeRate": 1,
      "paymentCurrencySymbol": "₺"
    },
    "totalPrice": {
      "basePayoutCurrencyCode": "USD",
      "basePayoutPrice": 3090,
      "convenienceFee": 0,
      "currencyCode": "TRY",
      "discount": 0,
      "discountPrice": 26900,
      "originalPrice": 26900,
      "originalUnitPrice": null,
      "unitPrice": null,
      "vat": 4103,
      "voucherDiscount": 0
    }
  }
}