{
  "id": "8f237c17ea5941aba9692a544db845c1",
  "price": {
    "totalPaymentPrice": {
      "paymentCurrencyAmount": 3120,
      "paymentCurrencyCode": "TRY",
      "paymentCurrencyExchangeRate": 1,
      "paymentCurrencySymbol": "₺"
    },
    "totalPrice": {
      "basePayoutCurrencyCode": "USD",
      "basePayoutPrice": 332,
      "convenienceFee": 0,
      "currencyCode": "TRY",
      "discount": 780,
      "discountPrice": 3120,
      "originalPrice": 3900,
      "originalUnitPrice": null,
      "unitPrice": null,
      "vat": 475,
      "voucherDiscount": 0
    }
  }
}