{
  "id": "94a4faacf2b9431c87d21b644971df3f",
  "price": {
    "totalPaymentPrice": {
      "paymentCurrencyAmount": 3099,
      "paymentCurrencyCode": "TRY",
      "paymentCurrencyExchangeRate": 1,
      "paymentCurrencySymbol": "₺"
    },
    "totalPrice": {
      "basePayoutCurrencyCode": "USD",
      "basePayoutPrice": 382,
      "convenienceFee": 0,
      "currencyCode": "TRY",
      "discount": 3100,
      "discountPrice": 3099,
      "originalPrice": 6199,
      "originalUnitPrice": null,
      "unitPrice": null,
      "vat": 472,
      "voucherDiscount": 0
    }
  }
}