{
  "id": "b6736b52c2354c94b2bb2c982b23971c",
  "price": {
    "totalPaymentPrice": {
      "paymentCurrencyAmount": 49500,
      "paymentCurrencyCode": "TRY",
      "paymentCurrencyExchangeRate": 1,
      "paymentCurrencySymbol": "₺"
    },
    "totalPrice": {
      "basePayoutCurrencyCode": "USD",
      "basePayoutPrice": 6017,
      "convenienceFee": 0,
      "currencyCode": "TRY",
      "discount": 0,
      "discountPrice": 49500,
      "originalPrice": 49500,
      "originalUnitPrice": null,
      "unitPrice": null,
      "vat": 7550,
      "voucherDiscount": 0
    }
  }
}