{
  "id": "f13ea94a77d0401f93b5569eea33c32f",
  "price": {
    "totalPaymentPrice": {
      "paymentCurrencyAmount": 29313,
      "paymentCurrencyCode": "TRY",
      "paymentCurrencyExchangeRate": 1,
      "paymentCurrencySymbol": "₺"
    },
    "totalPrice": {
      "basePayoutCurrencyCode": "USD",
      "basePayoutPrice": 3389,
      "convenienceFee": 0,
      "currencyCode": "TRY",
      "discount": 0,
      "discountPrice": 29313,
      "originalPrice": 29313,
      "originalUnitPrice": null,
      "unitPrice": null,
      "vat": 4471,
      "voucherDiscount": 0
    }
  }
}