{
  "id": "fc0961b1743c40f39447c6a27c3f0dd3",
  "price": {
    "totalPaymentPrice": {
      "paymentCurrencyAmount": 2070,
      "paymentCurrencyCode": "TRY",
      "paymentCurrencyExchangeRate": 1,
      "paymentCurrencySymbol": "₺"
    },
    "totalPrice": {
      "basePayoutCurrencyCode": "USD",
      "basePayoutPrice": 223,
      "convenienceFee": 0,
      "currencyCode": "TRY",
      "discount": 4830,
      "discountPrice": 2070,
      "originalPrice": 6900,
      "originalUnitPrice": null,
      "unitPrice": null,
      "vat": 316,
      "voucherDiscount": 0
    }
  }
}