{
  "id": "294ac2db4f3e4a30a712e1357a3ca2ae",
  "price": {
    "totalPaymentPrice": {
      "paymentCurrencyAmount": 699,
      "paymentCurrencyCode": "EUR",
      "paymentCurrencyExchangeRate": 1,
      "paymentCurrencySymbol": "€"
    },
    "totalPrice": {
      "basePayoutCurrencyCode": "USD",
      "basePayoutPrice": 767,
      "convenienceFee": 0,
      "currencyCode": "EUR",
      "discount": 0,
      "discountPrice": 699,
      "originalPrice": 699,
      "originalUnitPrice": null,
      "unitPrice": null,
      "vat": 49,
      "voucherDiscount": 0
    }
  }
}