{
  "id": "4d6f7c738cb6468d8fccce3de8d5d02e",
  "price": {
    "totalPaymentPrice": {
      "paymentCurrencyAmount": 3450,
      "paymentCurrencyCode": "CHF",
      "paymentCurrencyExchangeRate": 1,
      "paymentCurrencySymbol": "Fr."
    },
    "totalPrice": {
      "basePayoutCurrencyCode": "USD",
      "basePayoutPrice": 3540,
      "convenienceFee": 0,
      "currencyCode": "CHF",
      "discount": 0,
      "discountPrice": 3450,
      "originalPrice": 3450,
      "originalUnitPrice": null,
      "unitPrice": null,
      "vat": 247,
      "voucherDiscount": 0
    }
  }
}