{
  "id": "503a4fd4a6494e01a46723c8a09e70bf",
  "price": {
    "totalPaymentPrice": {
      "paymentCurrencyAmount": 430,
      "paymentCurrencyCode": "CHF",
      "paymentCurrencyExchangeRate": 1,
      "paymentCurrencySymbol": "Fr."
    },
    "totalPrice": {
      "basePayoutCurrencyCode": "USD",
      "basePayoutPrice": 449,
      "convenienceFee": 0,
      "currencyCode": "CHF",
      "discount": 0,
      "discountPrice": 430,
      "originalPrice": 430,
      "originalUnitPrice": null,
      "unitPrice": null,
      "vat": 31,
      "voucherDiscount": 0
    }
  }
}