{
  "id": "87042929b63047a49ae06a31f26825e7",
  "price": {
    "totalPaymentPrice": {
      "paymentCurrencyAmount": 6990,
      "paymentCurrencyCode": "CHF",
      "paymentCurrencyExchangeRate": 1,
      "paymentCurrencySymbol": "Fr."
    },
    "totalPrice": {
      "basePayoutCurrencyCode": "USD",
      "basePayoutPrice": 7254,
      "convenienceFee": 0,
      "currencyCode": "CHF",
      "discount": 0,
      "discountPrice": 6990,
      "originalPrice": 6990,
      "originalUnitPrice": null,
      "unitPrice": null,
      "vat": 500,
      "voucherDiscount": 0
    }
  }
}