{
  "id": "8806877c1c0d426ba71cb2a7a5e836ec",
  "price": {
    "totalPaymentPrice": {
      "paymentCurrencyAmount": 4299,
      "paymentCurrencyCode": "CHF",
      "paymentCurrencyExchangeRate": 1,
      "paymentCurrencySymbol": "Fr."
    },
    "totalPrice": {
      "basePayoutCurrencyCode": "USD",
      "basePayoutPrice": 4386,
      "convenienceFee": 0,
      "currencyCode": "CHF",
      "discount": 0,
      "discountPrice": 4299,
      "originalPrice": 4299,
      "originalUnitPrice": null,
      "unitPrice": null,
      "vat": 307,
      "voucherDiscount": 0
    }
  }
}