{
  "id": "8eeca1431d1b4010a12e6b3c8c400c94",
  "price": {
    "totalPaymentPrice": {
      "paymentCurrencyAmount": 4199,
      "paymentCurrencyCode": "CHF",
      "paymentCurrencyExchangeRate": 1,
      "paymentCurrencySymbol": "Fr."
    },
    "totalPrice": {
      "basePayoutCurrencyCode": "USD",
      "basePayoutPrice": 4311,
      "convenienceFee": 0,
      "currencyCode": "CHF",
      "discount": 1800,
      "discountPrice": 4199,
      "originalPrice": 5999,
      "originalUnitPrice": null,
      "unitPrice": null,
      "vat": 300,
      "voucherDiscount": 0
    }
  }
}