{
  "id": "1f7e992461c044b9972d0c3fb6a9277a",
  "price": {
    "totalPaymentPrice": {
      "paymentCurrencyAmount": 10759,
      "paymentCurrencyCode": "MXN",
      "paymentCurrencyExchangeRate": 1,
      "paymentCurrencySymbol": "$"
    },
    "totalPrice": {
      "basePayoutCurrencyCode": "USD",
      "basePayoutPrice": 502,
      "convenienceFee": 0,
      "currencyCode": "MXN",
      "discount": 16140,
      "discountPrice": 10759,
      "originalPrice": 26899,
      "originalUnitPrice": null,
      "unitPrice": null,
      "vat": 0,
      "voucherDiscount": 0
    }
  }
}