{
  "id": "59a0796c2a244fc28618bd6325a75fef",
  "price": {
    "totalPaymentPrice": {
      "paymentCurrencyAmount": 18524,
      "paymentCurrencyCode": "MXN",
      "paymentCurrencyExchangeRate": 1,
      "paymentCurrencySymbol": "$"
    },
    "totalPrice": {
      "basePayoutCurrencyCode": "USD",
      "basePayoutPrice": 874,
      "convenienceFee": 0,
      "currencyCode": "MXN",
      "discount": 6175,
      "discountPrice": 18524,
      "originalPrice": 24699,
      "originalUnitPrice": null,
      "unitPrice": null,
      "vat": 0,
      "voucherDiscount": 0
    }
  }
}