{
  "id": "607fa8cc3124428caa867595620011ff",
  "price": {
    "totalPaymentPrice": {
      "paymentCurrencyAmount": 22475,
      "paymentCurrencyCode": "DKK",
      "paymentCurrencyExchangeRate": 1,
      "paymentCurrencySymbol": "kr."
    },
    "totalPrice": {
      "basePayoutCurrencyCode": "USD",
      "basePayoutPrice": 2890,
      "convenienceFee": 0,
      "currencyCode": "DKK",
      "discount": 67425,
      "discountPrice": 22475,
      "originalPrice": 89900,
      "originalUnitPrice": null,
      "unitPrice": null,
      "vat": 4495,
      "voucherDiscount": 0
    }
  }
}