{
  "id": "9e32f311abd24c4aa4c7f9c5dce25e75",
  "price": {
    "totalPaymentPrice": {
      "paymentCurrencyAmount": 14817,
      "paymentCurrencyCode": "DKK",
      "paymentCurrencyExchangeRate": 1,
      "paymentCurrencySymbol": "kr."
    },
    "totalPrice": {
      "basePayoutCurrencyCode": "USD",
      "basePayoutPrice": 1807,
      "convenienceFee": 0,
      "currencyCode": "DKK",
      "discount": 30083,
      "discountPrice": 14817,
      "originalPrice": 44900,
      "originalUnitPrice": null,
      "unitPrice": null,
      "vat": 2963,
      "voucherDiscount": 0
    }
  }
}