{
  "id": "b352d9198af54297b462031c7a8c1c30",
  "price": {
    "totalPaymentPrice": {
      "paymentCurrencyAmount": 650,
      "paymentCurrencyCode": "DKK",
      "paymentCurrencyExchangeRate": null,
      "paymentCurrencySymbol": "kr."
    },
    "totalPrice": {
      "basePayoutCurrencyCode": "USD",
      "basePayoutPrice": 80,
      "convenienceFee": 0,
      "currencyCode": "USD",
      "discount": 0,
      "discountPrice": 100,
      "originalPrice": 100,
      "originalUnitPrice": null,
      "unitPrice": null,
      "vat": 20,
      "voucherDiscount": 0
    }
  }
}