{
  "id": "b83329b2de0640478b84f62de3e1ebe1",
  "price": {
    "totalPaymentPrice": {
      "paymentCurrencyAmount": 3400,
      "paymentCurrencyCode": "DKK",
      "paymentCurrencyExchangeRate": 1,
      "paymentCurrencySymbol": "kr."
    },
    "totalPrice": {
      "basePayoutCurrencyCode": "USD",
      "basePayoutPrice": 435,
      "convenienceFee": 0,
      "currencyCode": "DKK",
      "discount": 0,
      "discountPrice": 3400,
      "originalPrice": 3400,
      "originalUnitPrice": null,
      "unitPrice": null,
      "vat": 680,
      "voucherDiscount": 0
    }
  }
}