{
  "id": "2cb2b7b8565b4da793133214be09a6bc",
  "price": {
    "totalPaymentPrice": {
      "paymentCurrencyAmount": 3695,
      "paymentCurrencyCode": "ILS",
      "paymentCurrencyExchangeRate": 1,
      "paymentCurrencySymbol": "₪"
    },
    "totalPrice": {
      "basePayoutCurrencyCode": "USD",
      "basePayoutPrice": 1084,
      "convenienceFee": 0,
      "currencyCode": "ILS",
      "discount": 0,
      "discountPrice": 3695,
      "originalPrice": 3695,
      "originalUnitPrice": null,
      "unitPrice": null,
      "vat": 0,
      "voucherDiscount": 0
    }
  }
}