{
  "id": "3066be83ddf44541b9d6d7b05f09485f",
  "price": {
    "totalPaymentPrice": {
      "paymentCurrencyAmount": 23795,
      "paymentCurrencyCode": "ILS",
      "paymentCurrencyExchangeRate": 1,
      "paymentCurrencySymbol": "₪"
    },
    "totalPrice": {
      "basePayoutCurrencyCode": "USD",
      "basePayoutPrice": 6880,
      "convenienceFee": 0,
      "currencyCode": "ILS",
      "discount": 0,
      "discountPrice": 23795,
      "originalPrice": 23795,
      "originalUnitPrice": null,
      "unitPrice": null,
      "vat": 0,
      "voucherDiscount": 0
    }
  }
}