{
  "id": "62aec4264d80414b83ff8efc17a76b3b",
  "price": {
    "totalPaymentPrice": {
      "paymentCurrencyAmount": 399,
      "paymentCurrencyCode": "EUR",
      "paymentCurrencyExchangeRate": 1,
      "paymentCurrencySymbol": "€"
    },
    "totalPrice": {
      "basePayoutCurrencyCode": "USD",
      "basePayoutPrice": 393,
      "convenienceFee": 0,
      "currencyCode": "EUR",
      "discount": 0,
      "discountPrice": 399,
      "originalPrice": 399,
      "originalUnitPrice": null,
      "unitPrice": null,
      "vat": 69,
      "voucherDiscount": 0
    }
  }
}