{
  "id": "30e0d1b99ced430b825239b395ff140c",
  "price": {
    "totalPaymentPrice": {
      "paymentCurrencyAmount": 6255,
      "paymentCurrencyCode": "AED",
      "paymentCurrencyExchangeRate": 1,
      "paymentCurrencySymbol": "د.إ"
    },
    "totalPrice": {
      "basePayoutCurrencyCode": "USD",
      "basePayoutPrice": 1622,
      "convenienceFee": 0,
      "currencyCode": "AED",
      "discount": 12144,
      "discountPrice": 6255,
      "originalPrice": 18399,
      "originalUnitPrice": null,
      "unitPrice": null,
      "vat": 298,
      "voucherDiscount": 0
    }
  }
}