{
  "id": "6fe9d857f3a04f3c8c96218250c2035d",
  "price": {
    "totalPaymentPrice": {
      "paymentCurrencyAmount": 4399,
      "paymentCurrencyCode": "AED",
      "paymentCurrencyExchangeRate": 1,
      "paymentCurrencySymbol": "د.إ"
    },
    "totalPrice": {
      "basePayoutCurrencyCode": "USD",
      "basePayoutPrice": 1141,
      "convenienceFee": 0,
      "currencyCode": "AED",
      "discount": 0,
      "discountPrice": 4399,
      "originalPrice": 4399,
      "originalUnitPrice": null,
      "unitPrice": null,
      "vat": 209,
      "voucherDiscount": 0
    }
  }
}