{
  "id": "7981b6d8a37142b9aed96155b93ff8da",
  "price": {
    "totalPaymentPrice": {
      "paymentCurrencyAmount": 764,
      "paymentCurrencyCode": "USD",
      "paymentCurrencyExchangeRate": 1,
      "paymentCurrencySymbol": "$"
    },
    "totalPrice": {
      "basePayoutCurrencyCode": "USD",
      "basePayoutPrice": 729,
      "convenienceFee": 0,
      "currencyCode": "USD",
      "discount": 1485,
      "discountPrice": 764,
      "originalPrice": 2249,
      "originalUnitPrice": null,
      "unitPrice": null,
      "vat": 36,
      "voucherDiscount": 0
    }
  }
}