{
  "id": "dd845909e1504c048c14499eab60ec62",
  "price": {
    "totalPaymentPrice": {
      "paymentCurrencyAmount": 7259,
      "paymentCurrencyCode": "AED",
      "paymentCurrencyExchangeRate": 1,
      "paymentCurrencySymbol": "د.إ"
    },
    "totalPrice": {
      "basePayoutCurrencyCode": "USD",
      "basePayoutPrice": 1883,
      "convenienceFee": 0,
      "currencyCode": "AED",
      "discount": 14740,
      "discountPrice": 7259,
      "originalPrice": 21999,
      "originalUnitPrice": null,
      "unitPrice": null,
      "vat": 346,
      "voucherDiscount": 0
    }
  }
}