{
  "id": "f80e3e7fdac54ce0bc2cc3948796f837",
  "price": {
    "totalPaymentPrice": {
      "paymentCurrencyAmount": 199,
      "paymentCurrencyCode": "USD",
      "paymentCurrencyExchangeRate": 1,
      "paymentCurrencySymbol": "$"
    },
    "totalPrice": {
      "basePayoutCurrencyCode": "USD",
      "basePayoutPrice": 191,
      "convenienceFee": 0,
      "currencyCode": "USD",
      "discount": 200,
      "discountPrice": 199,
      "originalPrice": 399,
      "originalUnitPrice": null,
      "unitPrice": null,
      "vat": 9,
      "voucherDiscount": 0
    }
  }
}