{
  "id": "649633ef50aa42dc93d389092e2c834a",
  "price": {
    "totalPaymentPrice": {
      "paymentCurrencyAmount": 21500,
      "paymentCurrencyCode": "UAH",
      "paymentCurrencyExchangeRate": 1,
      "paymentCurrencySymbol": "₴"
    },
    "totalPrice": {
      "basePayoutCurrencyCode": "USD",
      "basePayoutPrice": 757,
      "convenienceFee": 0,
      "currencyCode": "UAH",
      "discount": 0,
      "discountPrice": 21500,
      "originalPrice": 21500,
      "originalUnitPrice": null,
      "unitPrice": null,
      "vat": 0,
      "voucherDiscount": 0
    }
  }
}