{
  "id": "89bf43761d39425e9068c37d1b83e63a",
  "price": {
    "totalPaymentPrice": {
      "paymentCurrencyAmount": 10900,
      "paymentCurrencyCode": "UAH",
      "paymentCurrencyExchangeRate": 1,
      "paymentCurrencySymbol": "₴"
    },
    "totalPrice": {
      "basePayoutCurrencyCode": "USD",
      "basePayoutPrice": 401,
      "convenienceFee": 0,
      "currencyCode": "UAH",
      "discount": 0,
      "discountPrice": 10900,
      "originalPrice": 10900,
      "originalUnitPrice": null,
      "unitPrice": null,
      "vat": 0,
      "voucherDiscount": 0
    }
  }
}