{
  "id": "aefb1bcd104f471eaf81d4bb4b5497fe",
  "price": {
    "totalPaymentPrice": {
      "paymentCurrencyAmount": 16900,
      "paymentCurrencyCode": "UAH",
      "paymentCurrencyExchangeRate": 1,
      "paymentCurrencySymbol": "₴"
    },
    "totalPrice": {
      "basePayoutCurrencyCode": "USD",
      "basePayoutPrice": 600,
      "convenienceFee": 0,
      "currencyCode": "UAH",
      "discount": 0,
      "discountPrice": 16900,
      "originalPrice": 16900,
      "originalUnitPrice": null,
      "unitPrice": null,
      "vat": 0,
      "voucherDiscount": 0
    }
  }
}