{
  "id": "d40519e5f9b145e397bb3d2e7b30ea17",
  "price": {
    "totalPaymentPrice": {
      "paymentCurrencyAmount": 0,
      "paymentCurrencyCode": "UAH",
      "paymentCurrencyExchangeRate": null,
      "paymentCurrencySymbol": "₴"
    },
    "totalPrice": {
      "basePayoutCurrencyCode": "USD",
      "basePayoutPrice": 0,
      "convenienceFee": 0,
      "currencyCode": "USD",
      "discount": 0,
      "discountPrice": 0,
      "originalPrice": 0,
      "originalUnitPrice": null,
      "unitPrice": null,
      "vat": 0,
      "voucherDiscount": 0
    }
  }
}