{
  "id": "e18ee56df6cd425c8615e2709f8e7bb1",
  "price": {
    "totalPaymentPrice": {
      "paymentCurrencyAmount": 21900,
      "paymentCurrencyCode": "UAH",
      "paymentCurrencyExchangeRate": 1,
      "paymentCurrencySymbol": "₴"
    },
    "totalPrice": {
      "basePayoutCurrencyCode": "USD",
      "basePayoutPrice": 776,
      "convenienceFee": 0,
      "currencyCode": "UAH",
      "discount": 0,
      "discountPrice": 21900,
      "originalPrice": 21900,
      "originalUnitPrice": null,
      "unitPrice": null,
      "vat": 0,
      "voucherDiscount": 0
    }
  }
}