{
  "id": "174e0d86d9e24880b0bf0e1721afa325",
  "price": {
    "totalPaymentPrice": {
      "paymentCurrencyAmount": 13900,
      "paymentCurrencyCode": "PLN",
      "paymentCurrencyExchangeRate": 1,
      "paymentCurrencySymbol": "zł"
    },
    "totalPrice": {
      "basePayoutCurrencyCode": "USD",
      "basePayoutPrice": 2924,
      "convenienceFee": 0,
      "currencyCode": "PLN",
      "discount": 0,
      "discountPrice": 13900,
      "originalPrice": 13900,
      "originalUnitPrice": null,
      "unitPrice": null,
      "vat": 2599,
      "voucherDiscount": 0
    }
  }
}