{
  "id": "69ea5dc33bb74632a6cfcdad236ecbcc",
  "price": {
    "totalPaymentPrice": {
      "paymentCurrencyAmount": 599,
      "paymentCurrencyCode": "PLN",
      "paymentCurrencyExchangeRate": 1,
      "paymentCurrencySymbol": "zł"
    },
    "totalPrice": {
      "basePayoutCurrencyCode": "USD",
      "basePayoutPrice": 126,
      "convenienceFee": 0,
      "currencyCode": "PLN",
      "discount": 0,
      "discountPrice": 599,
      "originalPrice": 599,
      "originalUnitPrice": null,
      "unitPrice": null,
      "vat": 112,
      "voucherDiscount": 0
    }
  }
}