{
  "id": "6ba21800aa6544e7a826b7e0ef0123af",
  "price": {
    "totalPaymentPrice": {
      "paymentCurrencyAmount": 14299,
      "paymentCurrencyCode": "PLN",
      "paymentCurrencyExchangeRate": 1,
      "paymentCurrencySymbol": "zł"
    },
    "totalPrice": {
      "basePayoutCurrencyCode": "USD",
      "basePayoutPrice": 3014,
      "convenienceFee": 0,
      "currencyCode": "PLN",
      "discount": 0,
      "discountPrice": 14299,
      "originalPrice": 14299,
      "originalUnitPrice": null,
      "unitPrice": null,
      "vat": 2673,
      "voucherDiscount": 0
    }
  }
}