{
  "id": "89bf43761d39425e9068c37d1b83e63a",
  "price": {
    "totalPaymentPrice": {
      "paymentCurrencyAmount": 2800,
      "paymentCurrencyCode": "PLN",
      "paymentCurrencyExchangeRate": 1,
      "paymentCurrencySymbol": "zł"
    },
    "totalPrice": {
      "basePayoutCurrencyCode": "USD",
      "basePayoutPrice": 619,
      "convenienceFee": 0,
      "currencyCode": "PLN",
      "discount": 0,
      "discountPrice": 2800,
      "originalPrice": 2800,
      "originalUnitPrice": null,
      "unitPrice": null,
      "vat": 524,
      "voucherDiscount": 0
    }
  }
}