{
  "id": "94a4faacf2b9431c87d21b644971df3f",
  "price": {
    "totalPaymentPrice": {
      "paymentCurrencyAmount": 4990,
      "paymentCurrencyCode": "PLN",
      "paymentCurrencyExchangeRate": 1,
      "paymentCurrencySymbol": "zł"
    },
    "totalPrice": {
      "basePayoutCurrencyCode": "USD",
      "basePayoutPrice": 1083,
      "convenienceFee": 0,
      "currencyCode": "PLN",
      "discount": 0,
      "discountPrice": 4990,
      "originalPrice": 4990,
      "originalUnitPrice": null,
      "unitPrice": null,
      "vat": 933,
      "voucherDiscount": 0
    }
  }
}