{
  "id": "b9229b0d1167444f87b297d2ff0827bd",
  "price": {
    "totalPaymentPrice": {
      "paymentCurrencyAmount": 14299,
      "paymentCurrencyCode": "PLN",
      "paymentCurrencyExchangeRate": 1,
      "paymentCurrencySymbol": "zł"
    },
    "totalPrice": {
      "basePayoutCurrencyCode": "USD",
      "basePayoutPrice": 2982,
      "convenienceFee": 0,
      "currencyCode": "PLN",
      "discount": 0,
      "discountPrice": 14299,
      "originalPrice": 14299,
      "originalUnitPrice": null,
      "unitPrice": null,
      "vat": 2673,
      "voucherDiscount": 0
    }
  }
}