{
  "id": "0823aa31fb7540db886871c5aa44dcc3",
  "price": {
    "totalPaymentPrice": {
      "paymentCurrencyAmount": 1447,
      "paymentCurrencyCode": "AUD",
      "paymentCurrencyExchangeRate": 1,
      "paymentCurrencySymbol": "$"
    },
    "totalPrice": {
      "basePayoutCurrencyCode": "USD",
      "basePayoutPrice": 939,
      "convenienceFee": 0,
      "currencyCode": "AUD",
      "discount": 1448,
      "discountPrice": 1447,
      "originalPrice": 2895,
      "originalUnitPrice": null,
      "unitPrice": null,
      "vat": 132,
      "voucherDiscount": 0
    }
  }
}