{
  "id": "68d29fbb437047adb3c6dd722634b84d",
  "price": {
    "totalPaymentPrice": {
      "paymentCurrencyAmount": 5497,
      "paymentCurrencyCode": "AUD",
      "paymentCurrencyExchangeRate": 1,
      "paymentCurrencySymbol": "$"
    },
    "totalPrice": {
      "basePayoutCurrencyCode": "USD",
      "basePayoutPrice": 3558,
      "convenienceFee": 0,
      "currencyCode": "AUD",
      "discount": 5498,
      "discountPrice": 5497,
      "originalPrice": 10995,
      "originalUnitPrice": null,
      "unitPrice": null,
      "vat": 499,
      "voucherDiscount": 0
    }
  }
}