{
  "id": "b1b202c965ba4e45b75289ae420d088c",
  "price": {
    "totalPaymentPrice": {
      "paymentCurrencyAmount": 6249,
      "paymentCurrencyCode": "AUD",
      "paymentCurrencyExchangeRate": 1,
      "paymentCurrencySymbol": "$"
    },
    "totalPrice": {
      "basePayoutCurrencyCode": "USD",
      "basePayoutPrice": 4181,
      "convenienceFee": 0,
      "currencyCode": "AUD",
      "discount": 6250,
      "discountPrice": 6249,
      "originalPrice": 12499,
      "originalUnitPrice": null,
      "unitPrice": null,
      "vat": 568,
      "voucherDiscount": 0
    }
  }
}