{
  "id": "b6a263b1e56b474a9aad3a5236a97052",
  "price": {
    "totalPaymentPrice": {
      "paymentCurrencyAmount": 9499,
      "paymentCurrencyCode": "EUR",
      "paymentCurrencyExchangeRate": 1,
      "paymentCurrencySymbol": "€"
    },
    "totalPrice": {
      "basePayoutCurrencyCode": "USD",
      "basePayoutPrice": 9072,
      "convenienceFee": 0,
      "currencyCode": "EUR",
      "discount": 0,
      "discountPrice": 9499,
      "originalPrice": 9499,
      "originalUnitPrice": null,
      "unitPrice": null,
      "vat": 1839,
      "voucherDiscount": 0
    }
  }
}