{
  "id": "3b58972f27fa4f9ab3c2fa936588fa93",
  "price": {
    "totalPaymentPrice": {
      "paymentCurrencyAmount": 36351,
      "paymentCurrencyCode": "RUB",
      "paymentCurrencyExchangeRate": 1,
      "paymentCurrencySymbol": "₽"
    },
    "totalPrice": {
      "basePayoutCurrencyCode": "USD",
      "basePayoutPrice": 413,
      "convenienceFee": 0,
      "currencyCode": "RUB",
      "discount": 0,
      "discountPrice": 36351,
      "originalPrice": 36351,
      "originalUnitPrice": null,
      "unitPrice": null,
      "vat": 6058,
      "voucherDiscount": 0
    }
  }
}