{
  "id": "96098502ae3c464294a8931b33d12bfd",
  "price": {
    "totalPaymentPrice": {
      "paymentCurrencyAmount": 202900,
      "paymentCurrencyCode": "RUB",
      "paymentCurrencyExchangeRate": 1,
      "paymentCurrencySymbol": "₽"
    },
    "totalPrice": {
      "basePayoutCurrencyCode": "USD",
      "basePayoutPrice": 2280,
      "convenienceFee": 0,
      "currencyCode": "RUB",
      "discount": 0,
      "discountPrice": 202900,
      "originalPrice": 202900,
      "originalUnitPrice": null,
      "unitPrice": null,
      "vat": 33817,
      "voucherDiscount": 0
    }
  }
}