{
  "id": "5d6c498807bd4a38a17ed9e51e18116b",
  "price": {
    "totalPaymentPrice": {
      "paymentCurrencyAmount": 7499,
      "paymentCurrencyCode": "BRL",
      "paymentCurrencyExchangeRate": 1,
      "paymentCurrencySymbol": "R$"
    },
    "totalPrice": {
      "basePayoutCurrencyCode": "USD",
      "basePayoutPrice": 1349,
      "convenienceFee": 0,
      "currencyCode": "BRL",
      "discount": 0,
      "discountPrice": 7499,
      "originalPrice": 7499,
      "originalUnitPrice": null,
      "unitPrice": null,
      "vat": 0,
      "voucherDiscount": 0
    }
  }
}