{
  "id": "6abd5c7aa1154b7ba6bd08159b52c1bd",
  "price": {
    "totalPaymentPrice": {
      "paymentCurrencyAmount": 6799,
      "paymentCurrencyCode": "BRL",
      "paymentCurrencyExchangeRate": 1,
      "paymentCurrencySymbol": "R$"
    },
    "totalPrice": {
      "basePayoutCurrencyCode": "USD",
      "basePayoutPrice": 1278,
      "convenienceFee": 0,
      "currencyCode": "BRL",
      "discount": 0,
      "discountPrice": 6799,
      "originalPrice": 6799,
      "originalUnitPrice": null,
      "unitPrice": null,
      "vat": 0,
      "voucherDiscount": 0
    }
  }
}