{
  "id": "be188e672dde452d9e517e5782e93f97",
  "price": {
    "totalPaymentPrice": {
      "paymentCurrencyAmount": 2849,
      "paymentCurrencyCode": "BRL",
      "paymentCurrencyExchangeRate": 1,
      "paymentCurrencySymbol": "R$"
    },
    "totalPrice": {
      "basePayoutCurrencyCode": "USD",
      "basePayoutPrice": 551,
      "convenienceFee": 0,
      "currencyCode": "BRL",
      "discount": 2850,
      "discountPrice": 2849,
      "originalPrice": 5699,
      "originalUnitPrice": null,
      "unitPrice": null,
      "vat": 0,
      "voucherDiscount": 0
    }
  }
}