{
  "id": "6defb63178384eef81732354fb8cb564",
  "price": {
    "totalPaymentPrice": {
      "paymentCurrencyAmount": 2799,
      "paymentCurrencyCode": "EUR",
      "paymentCurrencyExchangeRate": 1,
      "paymentCurrencySymbol": "€"
    },
    "totalPrice": {
      "basePayoutCurrencyCode": "USD",
      "basePayoutPrice": 2736,
      "convenienceFee": 0,
      "currencyCode": "EUR",
      "discount": 0,
      "discountPrice": 2799,
      "originalPrice": 2799,
      "originalUnitPrice": null,
      "unitPrice": null,
      "vat": 504,
      "voucherDiscount": 0
    }
  }
}