{
  "id": "0c4c8698988c41c6bdfd811ffccf4384",
  "price": {
    "totalPaymentPrice": {
      "paymentCurrencyAmount": 24800,
      "paymentCurrencyCode": "CZK",
      "paymentCurrencyExchangeRate": 1,
      "paymentCurrencySymbol": "Kč"
    },
    "totalPrice": {
      "basePayoutCurrencyCode": "USD",
      "basePayoutPrice": 931,
      "convenienceFee": 0,
      "currencyCode": "CZK",
      "discount": 6200,
      "discountPrice": 24800,
      "originalPrice": 31000,
      "originalUnitPrice": null,
      "unitPrice": null,
      "vat": 4304,
      "voucherDiscount": 0
    }
  }
}