{
  "id": "83ae3d8394ff4da9afa26fecab433be1",
  "price": {
    "totalPaymentPrice": {
      "paymentCurrencyAmount": 12975,
      "paymentCurrencyCode": "CZK",
      "paymentCurrencyExchangeRate": 1,
      "paymentCurrencySymbol": "Kč"
    },
    "totalPrice": {
      "basePayoutCurrencyCode": "USD",
      "basePayoutPrice": 489,
      "convenienceFee": 0,
      "currencyCode": "CZK",
      "discount": 38925,
      "discountPrice": 12975,
      "originalPrice": 51900,
      "originalUnitPrice": null,
      "unitPrice": null,
      "vat": 2252,
      "voucherDiscount": 0
    }
  }
}