{
  "id": "d79e3248103445809800dc37d0d4d086",
  "price": {
    "totalPaymentPrice": {
      "paymentCurrencyAmount": 210000,
      "paymentCurrencyCode": "CZK",
      "paymentCurrencyExchangeRate": 1,
      "paymentCurrencySymbol": "Kč"
    },
    "totalPrice": {
      "basePayoutCurrencyCode": "USD",
      "basePayoutPrice": 7729,
      "convenienceFee": 0,
      "currencyCode": "CZK",
      "discount": 0,
      "discountPrice": 210000,
      "originalPrice": 210000,
      "originalUnitPrice": null,
      "unitPrice": null,
      "vat": 36446,
      "voucherDiscount": 0
    }
  }
}