{
  "id": "13774284e1c04f9bb389c7b36ed49fb8",
  "price": {
    "totalPaymentPrice": {
      "paymentCurrencyAmount": 4400,
      "paymentCurrencyCode": "NOK",
      "paymentCurrencyExchangeRate": 1,
      "paymentCurrencySymbol": "kr"
    },
    "totalPrice": {
      "basePayoutCurrencyCode": "USD",
      "basePayoutPrice": 372,
      "convenienceFee": 0,
      "currencyCode": "NOK",
      "discount": 0,
      "discountPrice": 4400,
      "originalPrice": 4400,
      "originalUnitPrice": null,
      "unitPrice": null,
      "vat": 880,
      "voucherDiscount": 0
    }
  }
}