{
  "id": "5ba4f0c36ee94c30a45d8b0fd2143751",
  "price": {
    "totalPaymentPrice": {
      "paymentCurrencyAmount": 5000,
      "paymentCurrencyCode": "NOK",
      "paymentCurrencyExchangeRate": 1,
      "paymentCurrencySymbol": "kr"
    },
    "totalPrice": {
      "basePayoutCurrencyCode": "USD",
      "basePayoutPrice": 458,
      "convenienceFee": 0,
      "currencyCode": "NOK",
      "discount": 0,
      "discountPrice": 5000,
      "originalPrice": 5000,
      "originalUnitPrice": null,
      "unitPrice": null,
      "vat": 1000,
      "voucherDiscount": 0
    }
  }
}