{
  "id": "dc04085806054c1b927147e55fe7f4ac",
  "price": {
    "totalPaymentPrice": {
      "paymentCurrencyAmount": 2920,
      "paymentCurrencyCode": "NOK",
      "paymentCurrencyExchangeRate": 1,
      "paymentCurrencySymbol": "kr"
    },
    "totalPrice": {
      "basePayoutCurrencyCode": "USD",
      "basePayoutPrice": 256,
      "convenienceFee": 0,
      "currencyCode": "NOK",
      "discount": 8760,
      "discountPrice": 2920,
      "originalPrice": 11680,
      "originalUnitPrice": null,
      "unitPrice": null,
      "vat": 584,
      "voucherDiscount": 0
    }
  }
}