{
  "id": "7f981fff99e44998bf0de031eec36925",
  "price": {
    "totalPaymentPrice": {
      "paymentCurrencyAmount": 26880,
      "paymentCurrencyCode": "SEK",
      "paymentCurrencyExchangeRate": 1,
      "paymentCurrencySymbol": "kr"
    },
    "totalPrice": {
      "basePayoutCurrencyCode": "USD",
      "basePayoutPrice": 2450,
      "convenienceFee": 0,
      "currencyCode": "SEK",
      "discount": 11520,
      "discountPrice": 26880,
      "originalPrice": 38400,
      "originalUnitPrice": null,
      "unitPrice": null,
      "vat": 5376,
      "voucherDiscount": 0
    }
  }
}