{
  "id": "a14582f65ef545998d6012798513ae45",
  "price": {
    "totalPaymentPrice": {
      "paymentCurrencyAmount": 4200,
      "paymentCurrencyCode": "SEK",
      "paymentCurrencyExchangeRate": 1,
      "paymentCurrencySymbol": "kr"
    },
    "totalPrice": {
      "basePayoutCurrencyCode": "USD",
      "basePayoutPrice": 394,
      "convenienceFee": 0,
      "currencyCode": "SEK",
      "discount": 0,
      "discountPrice": 4200,
      "originalPrice": 4200,
      "originalUnitPrice": null,
      "unitPrice": null,
      "vat": 840,
      "voucherDiscount": 0
    }
  }
}