{
  "id": "a3b1812dc0d24cd6bfaa7032a5ae451d",
  "price": {
    "totalPaymentPrice": {
      "paymentCurrencyAmount": 5530,
      "paymentCurrencyCode": "SEK",
      "paymentCurrencyExchangeRate": 1,
      "paymentCurrencySymbol": "kr"
    },
    "totalPrice": {
      "basePayoutCurrencyCode": "USD",
      "basePayoutPrice": 504,
      "convenienceFee": 0,
      "currencyCode": "SEK",
      "discount": 2370,
      "discountPrice": 5530,
      "originalPrice": 7900,
      "originalUnitPrice": null,
      "unitPrice": null,
      "vat": 1106,
      "voucherDiscount": 0
    }
  }
}