{
  "id": "c46e7726fb6b465f8b1a749618edee64",
  "price": {
    "totalPaymentPrice": {
      "paymentCurrencyAmount": 8300,
      "paymentCurrencyCode": "SEK",
      "paymentCurrencyExchangeRate": 1,
      "paymentCurrencySymbol": "kr"
    },
    "totalPrice": {
      "basePayoutCurrencyCode": "USD",
      "basePayoutPrice": 742,
      "convenienceFee": 0,
      "currencyCode": "SEK",
      "discount": 0,
      "discountPrice": 8300,
      "originalPrice": 8300,
      "originalUnitPrice": null,
      "unitPrice": null,
      "vat": 1660,
      "voucherDiscount": 0
    }
  }
}