{
  "id": "61df2b608dc342b084e1a461740bd327",
  "price": {
    "totalPaymentPrice": {
      "paymentCurrencyAmount": 4399,
      "paymentCurrencyCode": "CAD",
      "paymentCurrencyExchangeRate": 1,
      "paymentCurrencySymbol": "$"
    },
    "totalPrice": {
      "basePayoutCurrencyCode": "USD",
      "basePayoutPrice": 3308,
      "convenienceFee": 0,
      "currencyCode": "CAD",
      "discount": 0,
      "discountPrice": 4399,
      "originalPrice": 4399,
      "originalUnitPrice": null,
      "unitPrice": null,
      "vat": 0,
      "voucherDiscount": 0
    }
  }
}