{
  "id": "97dae699db7d4961b079c212ea6e7f88",
  "price": {
    "totalPaymentPrice": {
      "paymentCurrencyAmount": 899,
      "paymentCurrencyCode": "CAD",
      "paymentCurrencyExchangeRate": 1,
      "paymentCurrencySymbol": "$"
    },
    "totalPrice": {
      "basePayoutCurrencyCode": "USD",
      "basePayoutPrice": 678,
      "convenienceFee": 0,
      "currencyCode": "CAD",
      "discount": 0,
      "discountPrice": 899,
      "originalPrice": 899,
      "originalUnitPrice": null,
      "unitPrice": null,
      "vat": 0,
      "voucherDiscount": 0
    }
  }
}