{
  "id": "a0bb13a219f747f88dff4c2a50b070c0",
  "price": {
    "totalPaymentPrice": {
      "paymentCurrencyAmount": 2299,
      "paymentCurrencyCode": "CAD",
      "paymentCurrencyExchangeRate": 1,
      "paymentCurrencySymbol": "$"
    },
    "totalPrice": {
      "basePayoutCurrencyCode": "USD",
      "basePayoutPrice": 1772,
      "convenienceFee": 0,
      "currencyCode": "CAD",
      "discount": 2300,
      "discountPrice": 2299,
      "originalPrice": 4599,
      "originalUnitPrice": null,
      "unitPrice": null,
      "vat": 0,
      "voucherDiscount": 0
    }
  }
}