{
  "id": "c34f7da8628c453fb0f442b31d858f9f",
  "price": {
    "totalPaymentPrice": {
      "paymentCurrencyAmount": 676,
      "paymentCurrencyCode": "CAD",
      "paymentCurrencyExchangeRate": null,
      "paymentCurrencySymbol": "$"
    },
    "totalPrice": {
      "basePayoutCurrencyCode": "USD",
      "basePayoutPrice": 499,
      "convenienceFee": 0,
      "currencyCode": "USD",
      "discount": 0,
      "discountPrice": 499,
      "originalPrice": 499,
      "originalUnitPrice": null,
      "unitPrice": null,
      "vat": 0,
      "voucherDiscount": 0
    }
  }
}