{
  "id": "cbab79cb3c774ad3bea17c5cb8d7b493",
  "price": {
    "totalPaymentPrice": {
      "paymentCurrencyAmount": 499,
      "paymentCurrencyCode": "CAD",
      "paymentCurrencyExchangeRate": 1,
      "paymentCurrencySymbol": "$"
    },
    "totalPrice": {
      "basePayoutCurrencyCode": "USD",
      "basePayoutPrice": 373,
      "convenienceFee": 0,
      "currencyCode": "CAD",
      "discount": 1500,
      "discountPrice": 499,
      "originalPrice": 1999,
      "originalUnitPrice": null,
      "unitPrice": null,
      "vat": 0,
      "voucherDiscount": 0
    }
  }
}