{
  "id": "42ccb715787e47f48648159060135ef1",
  "price": {
    "totalPaymentPrice": {
      "paymentCurrencyAmount": 992,
      "paymentCurrencyCode": "JPY",
      "paymentCurrencyExchangeRate": 1,
      "paymentCurrencySymbol": "¥"
    },
    "totalPrice": {
      "basePayoutCurrencyCode": "USD",
      "basePayoutPrice": 865,
      "convenienceFee": 0,
      "currencyCode": "JPY",
      "discount": 1488,
      "discountPrice": 992,
      "originalPrice": 2480,
      "originalUnitPrice": null,
      "unitPrice": null,
      "vat": 90,
      "voucherDiscount": 0
    }
  }
}