{
  "id": "9cf93671754649668f7a043b6200ff9b",
  "price": {
    "totalPaymentPrice": {
      "paymentCurrencyAmount": 5478,
      "paymentCurrencyCode": "JPY",
      "paymentCurrencyExchangeRate": 1,
      "paymentCurrencySymbol": "¥"
    },
    "totalPrice": {
      "basePayoutCurrencyCode": "USD",
      "basePayoutPrice": 4754,
      "convenienceFee": 0,
      "currencyCode": "JPY",
      "discount": 8218,
      "discountPrice": 5478,
      "originalPrice": 13696,
      "originalUnitPrice": null,
      "unitPrice": null,
      "vat": 498,
      "voucherDiscount": 0
    }
  }
}