{
  "id": "9f47dad590a44949b1e2eb519adc0ca1",
  "price": {
    "totalPaymentPrice": {
      "paymentCurrencyAmount": 1056,
      "paymentCurrencyCode": "JPY",
      "paymentCurrencyExchangeRate": 1,
      "paymentCurrencySymbol": "¥"
    },
    "totalPrice": {
      "basePayoutCurrencyCode": "USD",
      "basePayoutPrice": 904,
      "convenienceFee": 0,
      "currencyCode": "JPY",
      "discount": 1584,
      "discountPrice": 1056,
      "originalPrice": 2640,
      "originalUnitPrice": null,
      "unitPrice": null,
      "vat": 96,
      "voucherDiscount": 0
    }
  }
}