{
  "id": "ac3da74961c8413b9a63b4258cbc31f8",
  "price": {
    "totalPaymentPrice": {
      "paymentCurrencyAmount": 1980,
      "paymentCurrencyCode": "JPY",
      "paymentCurrencyExchangeRate": 1,
      "paymentCurrencySymbol": "¥"
    },
    "totalPrice": {
      "basePayoutCurrencyCode": "USD",
      "basePayoutPrice": 1684,
      "convenienceFee": 0,
      "currencyCode": "JPY",
      "discount": 0,
      "discountPrice": 1980,
      "originalPrice": 1980,
      "originalUnitPrice": null,
      "unitPrice": null,
      "vat": 180,
      "voucherDiscount": 0
    }
  }
}