{
  "id": "b0f6e38a93634a3bbfa3200c47379558",
  "price": {
    "totalPaymentPrice": {
      "paymentCurrencyAmount": 1980,
      "paymentCurrencyCode": "JPY",
      "paymentCurrencyExchangeRate": 1,
      "paymentCurrencySymbol": "¥"
    },
    "totalPrice": {
      "basePayoutCurrencyCode": "USD",
      "basePayoutPrice": 1710,
      "convenienceFee": 0,
      "currencyCode": "JPY",
      "discount": 5940,
      "discountPrice": 1980,
      "originalPrice": 7920,
      "originalUnitPrice": null,
      "unitPrice": null,
      "vat": 180,
      "voucherDiscount": 0
    }
  }
}