{
  "id": "ce72743eaedd40859b8af4122f096a73",
  "price": {
    "totalPaymentPrice": {
      "paymentCurrencyAmount": 9590,
      "paymentCurrencyCode": "KRW",
      "paymentCurrencyExchangeRate": 1,
      "paymentCurrencySymbol": "₩"
    },
    "totalPrice": {
      "basePayoutCurrencyCode": "USD",
      "basePayoutPrice": 745,
      "convenienceFee": 0,
      "currencyCode": "KRW",
      "discount": 6400,
      "discountPrice": 9590,
      "originalPrice": 15990,
      "originalUnitPrice": null,
      "unitPrice": null,
      "vat": 870,
      "voucherDiscount": 0
    }
  }
}