{
  "id": "df28d63878c34a2c94883265061c4676",
  "price": {
    "totalPaymentPrice": {
      "paymentCurrencyAmount": 90000,
      "paymentCurrencyCode": "KRW",
      "paymentCurrencyExchangeRate": 1,
      "paymentCurrencySymbol": "₩"
    },
    "totalPrice": {
      "basePayoutCurrencyCode": "USD",
      "basePayoutPrice": 7545,
      "convenienceFee": 0,
      "currencyCode": "KRW",
      "discount": 0,
      "discountPrice": 90000,
      "originalPrice": 90000,
      "originalUnitPrice": null,
      "unitPrice": null,
      "vat": 8180,
      "voucherDiscount": 0
    }
  }
}